wagtail_localize/__init__.py
wagtail_localize/apps.py
wagtail_localize/compat.py
wagtail_localize/components.py
wagtail_localize/fields.py
wagtail_localize/models.py
wagtail_localize/operations.py
wagtail_localize/strings.py
wagtail_localize/synctree.py
wagtail_localize/tasks.py
wagtail_localize/version.py
wagtail_localize/wagtail_hooks.py
wagtail_localize/locale/af/LC_MESSAGES/django.mo
wagtail_localize/locale/af/LC_MESSAGES/djangojs.mo
wagtail_localize/locale/af/LC_MESSAGES/djangojs.po
wagtail_localize/locale/ar/LC_MESSAGES/django.mo
wagtail_localize/locale/ar/LC_MESSAGES/django.po
wagtail_localize/locale/ar/LC_MESSAGES/djangojs.mo
wagtail_localize/locale/ar/LC_MESSAGES/djangojs.po
wagtail_localize/locale/az_AZ/LC_MESSAGES/django.mo
wagtail_localize/locale/az_AZ/LC_MESSAGES/django.po
wagtail_localize/locale/az_AZ/LC_MESSAGES/djangojs.mo
wagtail_localize/locale/az_AZ/LC_MESSAGES/djangojs.po
wagtail_localize/locale/be/LC_MESSAGES/django.mo
wagtail_localize/locale/be/LC_MESSAGES/django.po
wagtail_localize/locale/be/LC_MESSAGES/djangojs.mo
wagtail_localize/locale/be/LC_MESSAGES/djangojs.po
wagtail_localize/locale/bg/LC_MESSAGES/django.mo
wagtail_localize/locale/bg/LC_MESSAGES/django.po
wagtail_localize/locale/bg/LC_MESSAGES/djangojs.mo
wagtail_localize/locale/bg/LC_MESSAGES/djangojs.po
wagtail_localize/locale/bn/LC_MESSAGES/django.mo
wagtail_localize/locale/bn/LC_MESSAGES/django.po
wagtail_localize/locale/bn/LC_MESSAGES/djangojs.mo
wagtail_localize/locale/bn/LC_MESSAGES/djangojs.po
wagtail_localize/locale/ca/LC_MESSAGES/django.mo
wagtail_localize/locale/ca/LC_MESSAGES/django.po
wagtail_localize/locale/ca/LC_MESSAGES/djangojs.mo
wagtail_localize/locale/ca/LC_MESSAGES/djangojs.po
wagtail_localize/locale/cs/LC_MESSAGES/django.mo
wagtail_localize/locale/cs/LC_MESSAGES/django.po
wagtail_localize/locale/cs/LC_MESSAGES/djangojs.mo
wagtail_localize/locale/cs/LC_MESSAGES/djangojs.po
wagtail_localize/locale/cy/LC_MESSAGES/django.mo
wagtail_localize-1.13.dist-info/licenses/LICENSE
wagtail_localize-1.13.dist-info/WHEEL
wagtail_localize-1.13.dist-info/METADATA
wagtail_localize-1.13.dist-info/RECORD
