Metadata-Version: 2.4
Name: wagtail-localize
Version: 1.13
Summary: Translation plugin for Wagtail CMS
Author-email: Karl Hobley <karl@torchbox.com>
Maintainer-email: Dan Braghis <dan.braghis@torchbox.com>
Requires-Python: >=3.10
License-Expression: BSD-3-Clause
Classifier: Development Status :: 4 - Beta
Classifier: Intended Audience :: Developers
Classifier: Operating System :: OS Independent
Classifier: Programming Language :: Python
Classifier: Programming Language :: Python :: 3
Classifier: Programming Language :: Python :: 3.10
Classifier: Programming Language :: Python :: 3.11
Classifier: Programming Language :: Python :: 3.12
Classifier: Programming Language :: Python :: 3.13
Classifier: Programming Language :: Python :: 3.14
Classifier: Framework :: Django
Classifier: Framework :: Django :: 4.2
Classifier: Framework :: Django :: 5.1
Classifier: Framework :: Django :: 5.2
Classifier: Framework :: Wagtail
Classifier: Framework :: Wagtail :: 6
Classifier: Framework :: Wagtail :: 7
License-File: LICENSE
Requires-Dist: Django>=4.2
Requires-Dist: Wagtail>=6.3
Requires-Dist: polib>=1.1,<2.0
Requires-Dist: typing_extensions>=4.0
Requires-Dist: mkdocs==1.4.3 ; extra == "documentation"
Requires-Dist: mkdocs-material>=9.1,<10 ; extra == "documentation"
Requires-Dist: mkdocstrings[python]==0.22.0 ; extra == "documentation"
Requires-Dist: mkdocs-autorefs>=0.4.0,<0.5 ; extra == "documentation"
Requires-Dist: mkdocs-include-markdown-plugin>=4.0.4,<5 ; extra == "documentation"
Requires-Dist: pygments>=2.15,<2.16 ; extra == "documentation"
Requires-Dist: google-cloud-translate>=3.0.0 ; extra == "google"
Requires-Dist: pre-commit>=4.2.0,<6 ; extra == "linting"
Requires-Dist: dj-database-url>=2.1.0,<3 ; extra == "testing"
Requires-Dist: freezegun>=1.2,<2 ; extra == "testing"
Requires-Dist: django-rq>=2.5,<3.0 ; extra == "testing"
Requires-Dist: google-cloud-translate>=3.0.0 ; extra == "testing"
Requires-Dist: wagtail-modeladmin>=2.0,<3.0 ; extra == "testing"
Requires-Dist: coverage>=7.0,<8.0 ; extra == "testing"
Project-URL: Documentation, https://wagtail-localize.org
Project-URL: Home, https://wagtail-localize.org
Project-URL: Source, https://github.com/wagtail/wagtail-localize
Provides-Extra: documentation
Provides-Extra: google
Provides-Extra: linting
Provides-Extra: testing
